git_year/__init__.py
git_year/cli.py
git_year-0.5.3.dist-info/licenses/LICENSE
git_year-0.5.3.dist-info/METADATA
git_year-0.5.3.dist-info/WHEEL
git_year-0.5.3.dist-info/entry_points.txt
git_year-0.5.3.dist-info/top_level.txt
git_year-0.5.3.dist-info/RECORD
