Metadata-Version: 2.4
Name: git-year
Version: 0.5.3
Summary: A compact terminal heatmap showing one year of Git commits (like GitHub contributions, but with compact bars instead of squares, to fit into a smaller terminal window)
Author-email: Serge Velbovets <serge@velbix.com>
License: MIT
Requires-Python: >=3.8
License-File: LICENSE
Dynamic: license-file
